[
	{
		"key": "dbln",
		"value": "%7B%22100094304555476%22%3A%22v2h9zR24%22%7D",
		"domain": "facebook.com",
		"path": "/login/device-based/",
		"hostOnly": false,
		"creation": "2025-02-11T16:13:12.113Z",
		"lastAccessed": "2025-02-11T16:13:12.134Z"
	},
	{
		"key": "datr",
		"value": "rv5wZ3kfLRusav_HjZp--0lh",
		"domain": "facebook.com",
		"path": "/",
		"hostOnly": false,
		"creation": "2025-02-11T16:13:12.134Z",
		"lastAccessed": "2025-02-11T16:13:12.134Z"
	},
	{
		"key": "sb",
		"value": "r_5wZ3pneeCe7i2t5dZp9oLr",
		"domain": "facebook.com",
		"path": "/",
		"hostOnly": false,
		"creation": "2025-02-11T16:13:12.134Z",
		"lastAccessed": "2025-02-11T16:13:12.134Z"
	},
	{
		"key": "ps_l",
		"value": "1",
		"domain": "facebook.com",
		"path": "/",
		"hostOnly": false,
		"creation": "2025-02-11T16:13:12.134Z",
		"lastAccessed": "2025-02-11T16:13:12.134Z"
	},
	{
		"key": "ps_n",
		"value": "1",
		"domain": "facebook.com",
		"path": "/",
		"hostOnly": false,
		"creation": "2025-02-11T16:13:12.134Z",
		"lastAccessed": "2025-02-11T16:13:12.134Z"
	},
	{
		"key": "vpd",
		"value": "v1%3B774x412x1.75",
		"domain": "facebook.com",
		"path": "/",
		"hostOnly": false,
		"creation": "2025-02-11T16:13:12.134Z",
		"lastAccessed": "2025-02-11T16:13:12.134Z"
	},
	{
		"key": "c_user",
		"value": "100087708704742",
		"domain": "facebook.com",
		"path": "/",
		"hostOnly": false,
		"creation": "2025-02-11T16:13:12.134Z",
		"lastAccessed": "2025-02-11T16:13:12.134Z"
	},
	{
		"key": "fr",
		"value": "1Pa8ORJrMPEkpr0Eq.AWUPG6GDm0jWaF9fIhB60y-FDy4.BndZVN..AAA.0.0.Bnk3Vx.AWXi6tdNulw",
		"domain": "facebook.com",
		"path": "/",
		"hostOnly": false,
		"creation": "2025-02-11T16:13:12.134Z",
		"lastAccessed": "2025-02-11T16:13:12.134Z"
	},
	{
		"key": "xs",
		"value": "46%3Aa38KJWg2VsjjXg%3A2%3A1737717107%3A-1%3A5122",
		"domain": "facebook.com",
		"path": "/",
		"hostOnly": false,
		"creation": "2025-02-11T16:13:12.134Z",
		"lastAccessed": "2025-02-11T16:13:12.134Z"
	},
	{
		"key": "locale",
		"value": "en_GB",
		"domain": "facebook.com",
		"path": "/",
		"hostOnly": false,
		"creation": "2025-02-11T16:13:12.134Z",
		"lastAccessed": "2025-02-11T16:13:12.134Z"
	},
	{
		"key": "fbl_st",
		"value": "100628031%3BT%3A28988099",
		"domain": "facebook.com",
		"path": "/",
		"hostOnly": false,
		"creation": "2025-02-11T16:13:12.134Z",
		"lastAccessed": "2025-02-11T16:13:12.134Z"
	},
	{
		"key": "wl_cbv",
		"value": "v2%3Bclient_version%3A2738%3Btimestamp%3A1739285934%3BCRCM%3A120303621",
		"domain": "facebook.com",
		"path": "/",
		"hostOnly": false,
		"creation": "2025-02-11T16:13:12.134Z",
		"lastAccessed": "2025-02-11T16:13:12.134Z"
	}
]
